appdevcommons/__init__.py
appdevcommons/hash_generator.py
appdevcommons/kms_encryptor.py
appdevcommons/unique_id.py
appdevcommons-0.1.4.dist-info/licenses/LICENSE
appdevcommons-0.1.4.dist-info/METADATA
appdevcommons-0.1.4.dist-info/WHEEL
appdevcommons-0.1.4.dist-info/top_level.txt
appdevcommons-0.1.4.dist-info/RECORD
