Metadata-Version: 2.4
Name: appdevcommons
Version: 0.1.4
Summary: A collection of common utilities and functionalities for Python applications
Author-email: Your Name <your.email@example.com>
License: MIT
Project-URL: Homepage, https://github.com/sl5234/AppDevCommons
Project-URL: Documentation, https://github.com/sl5234/AppDevCommons#readme
Project-URL: Repository, https://github.com/sl5234/AppDevCommons
Project-URL: Issues, https://github.com/sl5234/AppDevCommons/issues
Keywords: utilities,common,helpers,tools
Classifier: Development Status :: 3 - Alpha
Classifier: Intended Audience :: Developers
Classifier: License :: OSI Approved :: MIT License
Classifier: Programming Language :: Python :: 3
Classifier: Programming Language :: Python :: 3.10
Classifier: Programming Language :: Python :: 3.11
Classifier: Programming Language :: Python :: 3.12
Requires-Python: >=3.10
License-File: LICENSE
Requires-Dist: boto3>=1.26.0
Provides-Extra: dev
Requires-Dist: pytest>=7.0.0; extra == "dev"
Requires-Dist: pytest-cov>=4.0.0; extra == "dev"
Requires-Dist: black>=23.0.0; extra == "dev"
Requires-Dist: flake8>=6.0.0; extra == "dev"
Requires-Dist: mypy>=1.0.0; extra == "dev"
Requires-Dist: ruff>=0.1.0; extra == "dev"
Dynamic: license-file
